CHANGELOG
MANIFEST.in
setup.py
django_filepicker/__init__.py
django_filepicker/context_processors.py
django_filepicker/forms.py
django_filepicker/middleware.py
django_filepicker/models.py
django_filepicker/utils.py
django_filepicker/widgets.py
django_filepicker.egg-info/PKG-INFO
django_filepicker.egg-info/SOURCES.txt
django_filepicker.egg-info/dependency_links.txt
django_filepicker.egg-info/not-zip-safe
django_filepicker.egg-info/requires.txt
django_filepicker.egg-info/top_level.txt