Metadata-Version: 1.0
Name: django-filepicker
Version: 0.2.2
Summary: Official Filepicker Django Library
Home-page: http://developers.filepicker.io/
Author: Filepicker.io
Author-email: contact@filepicker.io
License: BSD
Platform: UNKNOWN
